baozi/.gitignore
baozi/__init__.py
baozi/baozi.py
baozi/error.py
baozi/frozen.py
baozi/slots.py
baozi/typecast.py
baozi-0.0.6.dist-info/LICENSE
baozi-0.0.6.dist-info/METADATA
baozi-0.0.6.dist-info/WHEEL
baozi-0.0.6.dist-info/RECORD
