Metadata-Version: 2.1
Name: baozi
Version: 0.0.6
Summary: 
License: MIT
Author: race
Author-email: raceychan@gmail.com
Requires-Python: >=3.11,<4.0
Classifier: License :: OSI Approved :: MIT License
Classifier: Programming Language :: Python :: 3
Classifier: Programming Language :: Python :: 3.11
Classifier: Programming Language :: Python :: 3.12
